url64/__init__.py
url64/url64.py
url64-0.1.0.dist-info/LICENSE
url64-0.1.0.dist-info/METADATA
url64-0.1.0.dist-info/WHEEL
url64-0.1.0.dist-info/top_level.txt
url64-0.1.0.dist-info/RECORD
