Metadata-Version: 2.1
Name: url64
Version: 0.1.0
Summary: url64 decode/encode for python
Home-page: https://github.com/puria/url64
Author: Puria Nafisi Azizi
Author-email: puria@dyne.org
License: Apache-2.0
Project-URL: Source Code, https://github.com/puria/url64
Keywords: serialization url64 encoder decoder
Platform: UNKNOWN
Classifier: Development Status :: 5 - Production/Stable
Classifier: License :: OSI Approved :: Apache Software License
Classifier: Intended Audience :: Developers
Classifier: Operating System :: POSIX :: Linux
Classifier: Operating System :: MacOS :: MacOS X
Classifier: Programming Language :: Python
License-File: LICENSE
Provides-Extra: test
Requires-Dist: pytest ; extra == 'test'
Requires-Dist: pytest-cov ; extra == 'test'
